nascoder/__init__.py
nascoder/cli.py
nascoder-1.0.0.dist-info/licenses/LICENSE
nascoder-1.0.0.dist-info/METADATA
nascoder-1.0.0.dist-info/WHEEL
nascoder-1.0.0.dist-info/entry_points.txt
nascoder-1.0.0.dist-info/top_level.txt
nascoder-1.0.0.dist-info/RECORD
