Metadata-Version: 2.4
Name: nascoder
Version: 1.0.0
Summary: AI Assistant powered by AWS Bedrock with Claude models
Home-page: https://github.com/freelancernasim/nascoder
Author: NasCoder Team
Author-email: NasCoder Team <contact@nascoder.dev>
License: MIT
Project-URL: Homepage, https://github.com/freelancernasim/nascoder
Project-URL: Repository, https://github.com/freelancernasim/nascoder
Project-URL: Issues, https://github.com/freelancernasim/nascoder/issues
Keywords: ai,aws,bedrock,claude,cli,assistant
Classifier: Development Status :: 4 - Beta
Classifier: Intended Audience :: Developers
Classifier: License :: OSI Approved :: MIT License
Classifier: Operating System :: OS Independent
Classifier: Programming Language :: Python :: 3
Classifier: Programming Language :: Python :: 3.8
Classifier: Programming Language :: Python :: 3.9
Classifier: Programming Language :: Python :: 3.10
Classifier: Programming Language :: Python :: 3.11
Classifier: Programming Language :: Python :: 3.12
Requires-Python: >=3.8
License-File: LICENSE
Requires-Dist: boto3>=1.34.0
Requires-Dist: click>=8.1.0
Requires-Dist: rich>=13.0.0
Requires-Dist: python-dotenv>=1.0.0
Dynamic: author
Dynamic: home-page
Dynamic: license-file
Dynamic: requires-python
